tracecode/__init__.py
tracecode/conf.py
tracecode/pathutils.py
tracecode/tracecode.py
tracecode/tracer.py
tracecode/_vendor/__init__.py
tracecode/_vendor/docopt.py
tracecode/_vendor/altgraph/Dot.py
tracecode/_vendor/altgraph/Graph.py
tracecode/_vendor/altgraph/GraphAlgo.py
tracecode/_vendor/altgraph/GraphStat.py
tracecode/_vendor/altgraph/GraphUtil.py
tracecode/_vendor/altgraph/ObjectGraph.py
tracecode/_vendor/altgraph/__init__.py
tracecode/_vendor/altgraph-0.17.3.dist-info/INSTALLER
tracecode/_vendor/altgraph-0.17.3.dist-info/LICENSE
tracecode/_vendor/altgraph-0.17.3.dist-info/METADATA
tracecode/_vendor/altgraph-0.17.3.dist-info/RECORD
tracecode/_vendor/altgraph-0.17.3.dist-info/REQUESTED
tracecode/_vendor/altgraph-0.17.3.dist-info/WHEEL
tracecode/_vendor/altgraph-0.17.3.dist-info/top_level.txt
tracecode/_vendor/altgraph-0.17.3.dist-info/zip-safe
tracecode/_vendor/docopt-0.6.2.dist-info/INSTALLER
tracecode/_vendor/docopt-0.6.2.dist-info/LICENSE-MIT
tracecode/_vendor/docopt-0.6.2.dist-info/METADATA
tracecode/_vendor/docopt-0.6.2.dist-info/RECORD
tracecode/_vendor/docopt-0.6.2.dist-info/REQUESTED
tracecode/_vendor/docopt-0.6.2.dist-info/WHEEL
tracecode/_vendor/docopt-0.6.2.dist-info/top_level.txt
tracecode_toolkit_strace-0.21.0.dist-info/AUTHORS.rst
tracecode_toolkit_strace-0.21.0.dist-info/CHANGELOG.rst
tracecode_toolkit_strace-0.21.0.dist-info/METADATA
tracecode_toolkit_strace-0.21.0.dist-info/NOTICE
tracecode_toolkit_strace-0.21.0.dist-info/WHEEL
tracecode_toolkit_strace-0.21.0.dist-info/apache-2.0.LICENSE
tracecode_toolkit_strace-0.21.0.dist-info/entry_points.txt
tracecode_toolkit_strace-0.21.0.dist-info/top_level.txt
tracecode_toolkit_strace-0.21.0.dist-info/RECORD
