Metadata-Version: 2.1
Name: tracecode-toolkit-strace
Version: 0.21.0
Summary: TraceCode toolkit "strace" is dynamic build tracer and grapher
Home-page: https://github.com/nexB/tracecode-toolkit-strace
Author: nexB. Inc. and others
Author-email: info@aboutcode.org
License: Apache-2.0
Keywords: utilities,tracecode,strace,tracing,build,scancode
Classifier: Development Status :: 4 - Beta
Classifier: Intended Audience :: Developers
Classifier: Programming Language :: Python :: 3
Classifier: Programming Language :: Python :: 3 :: Only
Classifier: Topic :: Software Development
Classifier: Topic :: Utilities
Requires-Python: >=3.6.*
License-File: apache-2.0.LICENSE
License-File: NOTICE
License-File: AUTHORS.rst
License-File: CHANGELOG.rst
Provides-Extra: docs
Requires-Dist: Sphinx (>=3.3.1) ; extra == 'docs'
Requires-Dist: sphinx-rtd-theme (>=0.5.0) ; extra == 'docs'
Requires-Dist: doc8 (>=0.8.1) ; extra == 'docs'
Provides-Extra: testing
Requires-Dist: pytest (!=7.0.0,>=6) ; extra == 'testing'
Requires-Dist: pytest-xdist (>=2) ; extra == 'testing'
Requires-Dist: aboutcode-toolkit (>=6.0.0) ; extra == 'testing'
Requires-Dist: black ; extra == 'testing'
Requires-Dist: vendorize ; extra == 'testing'
